{
  "cities": [
    {
      "cityName": "Lisbon",
      "country": "Portugal",
      "emoji": "🇵🇹",
      "date": "2027-10-31T15:59:59.138Z",
      "notes": "My favorite city so far!",
      "position": {
        "lat": 38.727881642324164,
        "lng": -9.140900099907554
      },
      "id": "73930385"
    },
    {
      "cityName": "Madrid",
      "country": "Spain",
      "emoji": "🇪🇸",
      "date": "2027-07-15T08:22:53.976Z",
      "notes": "",
      "position": {
        "lat": 40.46635901755316,
        "lng": -3.7133789062500004
      },
      "id": "17806751"
    },
    {
      "cityName": "Berlin",
      "country": "Germany",
      "emoji": "🇩🇪",
      "date": "2027-02-12T09:24:11.863Z",
      "notes": "Amazing 😃",
      "position": {
        "lat": 52.53586782505711,
        "lng": 13.376933665713324
      },
      "id": "98443197"
    },
    {
      "id": "421d",
      "cityName": "Lisbon",
      "country": "Portugal",
      "emoji": "PT",
      "date": "2024-08-20T04:00:00.000Z",
      "notes": "",
      "position": {
        "lat": "38.72971616110815",
        "lng": "-9.142960211256508"
      }
    },
    {
      "id": "8258",
      "cityName": "Lisbon",
      "country": "Portugal",
      "emoji": "PT",
      "date": "2024-08-30T04:00:00.000Z",
      "notes": "",
      "position": {
        "lat": "38.73400094703239",
        "lng": "-9.143642651359336"
      }
    },
    {
      "id": "ed38",
      "cityName": "Lisbon",
      "country": "Portugal",
      "emoji": "PT",
      "date": "2024-08-02T04:00:00.000Z",
      "notes": "",
      "position": {
        "lat": "38.74002622872044",
        "lng": "-9.138990411841014"
      }
    },
    {
      "id": "0420",
      "cityName": "Lisbon",
      "country": "Portugal",
      "emoji": "PT",
      "date": "2024-08-02T04:00:00.000Z",
      "notes": "",
      "position": {
        "lat": "38.74022786036853",
        "lng": "-9.141588602402871"
      }
    },
    {
      "id": "ea92",
      "cityName": "Bakanas",
      "country": "Kazakhstan",
      "emoji": "KZ",
      "date": "2024-08-29T04:00:00.000Z",
      "notes": "",
      "position": {
        "lat": "45.10559271572062",
        "lng": "75.7196435523251"
      }
    },
    {
      "id": "58e4",
      "cityName": "Tobruk",
      "country": "Libya",
      "emoji": "LY",
      "date": "2024-08-31T04:00:00.000Z",
      "notes": "",
      "position": {
        "lat": "32.02422766191497",
        "lng": "24.989105260629053"
      }
    },
    {
      "id": "79cd",
      "cityName": "Zyryanka",
      "country": "Russian Federation (the)",
      "emoji": "RU",
      "date": "2024-08-26T04:00:00.000Z",
      "notes": "",
      "position": {
        "lat": "64.47965474764611",
        "lng": "148.5479934527669"
      }
    },
    {
      "id": "bd05",
      "cityName": "Haldimand County",
      "country": "Canada",
      "emoji": "CA",
      "date": "2024-08-06T04:00:00.000Z",
      "notes": "",
      "position": {
        "lat": "42.815626719869584",
        "lng": "-79.82263959077065"
      }
    },
    {
      "id": "7a4e",
      "cityName": "Tazrouk",
      "country": "Algeria",
      "emoji": "DZ",
      "date": "2024-08-02T04:00:00.000Z",
      "notes": "",
      "position": {
        "lat": "22.259325352404293",
        "lng": "7.610228471010566"
      }
    }
  ]
}